pppine/__init__.py
pppine/django.py
pppine/middleware.py
pppine/misc.py
pppine/encoders/__init__.py
pppine/encoders/json.py
pppine/python/__init__.py
pppine/python/contact.py
pppine/python/datetime.py
pppine/python/general.py
pppine/python/generators.py
pppine/python/url.py
pppine-1.3.2.dist-info/LICENSE
pppine-1.3.2.dist-info/METADATA
pppine-1.3.2.dist-info/WHEEL
pppine-1.3.2.dist-info/top_level.txt
pppine-1.3.2.dist-info/RECORD
