Metadata-Version: 2.1
Name: pppine
Version: 1.3.2
Summary: A collection of miscellaneous functions and utilities for Python and/or Django.
Home-page: https://github.com/mkopani/pppine
Author: Mark Kopani
Author-email: mkopani@gmail.com
License: MIT
Platform: UNKNOWN
Classifier: Programming Language :: Python :: 3
Classifier: License :: OSI Approved :: MIT License
Classifier: Operating System :: OS Independent
Requires-Python: >=3.6
License-File: LICENSE
Requires-Dist: setuptools (>=42)
Requires-Dist: wheel
Requires-Dist: python-magic
Requires-Dist: pytz
Requires-Dist: shortuuid
Requires-Dist: phonenumbers
Requires-Dist: pymongo
